hexaeight_mcp_client/__init__.py
hexaeight_mcp_client/adapters.py
hexaeight_mcp_client/agent_manager.py
hexaeight_mcp_client/client.py
hexaeight_mcp_client/exceptions.py
hexaeight_mcp_client/py.typed
hexaeight_mcp_client/cli/__init__.py
hexaeight_mcp_client/cli/agent_generation.py
hexaeight_mcp_client/cli/concepts_presentation.py
hexaeight_mcp_client/cli/directory_setup.py
hexaeight_mcp_client/cli/license_activation.py
hexaeight_mcp_client/cli/main.py
hexaeight_mcp_client/cli/portable_setup.py
hexaeight_mcp_client/cli/prerequisites.py
hexaeight_mcp_client/cli/sample_deployment.py
hexaeight_mcp_client/cli/utils.py
hexaeight_mcp_client/templates/license_activation_guide.md
hexaeight_mcp_client/templates/agents/autogen_weather_agent.py
hexaeight_mcp_client/templates/agents/crewai_weather_agent.py
hexaeight_mcp_client/templates/agents/langchain_weather_agent.py
hexaeight_mcp_client/templates/agents/shared_components.py
hexaeight_mcp_client/templates/configs/README.md
hexaeight_mcp_client/templates/scripts/create_agents_env.sh
hexaeight_mcp_client-1.6.809.dist-info/licenses/LICENSE
hexaeight_mcp_client-1.6.809.dist-info/METADATA
hexaeight_mcp_client-1.6.809.dist-info/WHEEL
hexaeight_mcp_client-1.6.809.dist-info/entry_points.txt
hexaeight_mcp_client-1.6.809.dist-info/top_level.txt
hexaeight_mcp_client-1.6.809.dist-info/RECORD
