Metadata-Version: 2.4
Name: hexaeight-mcp-client
Version: 1.6.809
Summary: Framework-agnostic MCP client integration for HexaEight agents
Author-email: HexaEight <support@hexaeight.com>
License-Expression: MIT
Project-URL: Homepage, https://github.com/HexaEightTeam/hexaeight-mcp-client
Project-URL: Documentation, https://github.com/HexaEightTeam/hexaeight-mcp-client/blob/main/README.md
Project-URL: Repository, https://github.com/HexaEightTeam/hexaeight-mcp-client.git
Project-URL: Issues, https://github.com/HexaEightTeam/hexaeight-mcp-client/issues
Keywords: mcp,agent,hexaeight,multi-agent,identity,security,autogen,crewai,langchain
Classifier: Development Status :: 4 - Beta
Classifier: Intended Audience :: Developers
Classifier: Programming Language :: Python :: 3
Classifier: Programming Language :: Python :: 3.8
Classifier: Programming Language :: Python :: 3.9
Classifier: Programming Language :: Python :: 3.10
Classifier: Programming Language :: Python :: 3.11
Classifier: Programming Language :: Python :: 3.12
Classifier: Topic :: Software Development :: Libraries :: Python Modules
Classifier: Topic :: Scientific/Engineering :: Artificial Intelligence
Requires-Python: >=3.8
License-File: LICENSE
Requires-Dist: hexaeight-agent>=1.6.808
Provides-Extra: autogen
Requires-Dist: pyautogen>=0.2.0; extra == "autogen"
Provides-Extra: crewai
Requires-Dist: crewai>=0.1.0; extra == "crewai"
Provides-Extra: langchain
Requires-Dist: langchain>=0.1.0; extra == "langchain"
Provides-Extra: all
Requires-Dist: pyautogen>=0.2.0; extra == "all"
Requires-Dist: crewai>=0.1.0; extra == "all"
Requires-Dist: langchain>=0.1.0; extra == "all"
Provides-Extra: dev
Requires-Dist: pytest>=7.0.0; extra == "dev"
Requires-Dist: pytest-asyncio>=0.21.0; extra == "dev"
Requires-Dist: black>=22.0.0; extra == "dev"
Requires-Dist: flake8>=4.0.0; extra == "dev"
Requires-Dist: build>=0.10.0; extra == "dev"
Requires-Dist: twine>=4.0.0; extra == "dev"
Dynamic: license-file
